ipysimplebind/__init__.py
ipysimplebind/_version.py
ipysimplebind/gen.py
ipysimplebind-0.1.9.dist-info/LICENSE
ipysimplebind-0.1.9.dist-info/METADATA
ipysimplebind-0.1.9.dist-info/WHEEL
ipysimplebind-0.1.9.dist-info/top_level.txt
ipysimplebind-0.1.9.dist-info/RECORD
