Metadata-Version: 2.1
Name: ipysimplebind
Version: 0.1.9
Summary: Rapid JS-Python binding for ipython widgets, for HTML/JS apps
Home-page: https://github.com/paultiq/ipysimplebind
Author: Paul Timmins
Author-email: paul@iqmo.com
Keywords: ipython notebook jupyter anywidget html js javascript
License-File: LICENSE
Requires-Dist: anywidget
